__init__.py
r3f.py
r3f-2.1.10.dist-info/licenses/LICENSE.txt
r3f-2.1.10.dist-info/METADATA
r3f-2.1.10.dist-info/WHEEL
r3f-2.1.10.dist-info/top_level.txt
r3f-2.1.10.dist-info/RECORD
