Metadata-Version: 2.4
Name: r3f
Version: 2.1.10
Summary: A library for three-dimensional, reference-frame conversions
Author-email: David Woodburn <david.woodburn@icloud.com>
License: MIT
Project-URL: Homepage, https://gitlab.com/davidwoodburn/r3f
Project-URL: Bug Tracker, https://gitlab.com/davidwoodburn/r3f/-/issues
Classifier: Programming Language :: Python :: 3
Classifier: License :: OSI Approved :: MIT License
Classifier: Operating System :: OS Independent
Requires-Python: >=3.6
License-File: LICENSE.txt
Requires-Dist: numpy
Provides-Extra: test
Requires-Dist: pytest; extra == "test"
Dynamic: license-file
